lyra_v2_action_signing/__init__.py
lyra_v2_action_signing/signed_action.py
lyra_v2_action_signing/utils.py
lyra_v2_action_signing/module_data/__init__.py
lyra_v2_action_signing/module_data/deposit.py
lyra_v2_action_signing/module_data/module_data.py
lyra_v2_action_signing/module_data/rfq.py
lyra_v2_action_signing/module_data/trade.py
lyra_v2_action_signing/module_data/transfer_erc20.py
lyra_v2_action_signing/module_data/transfer_positions.py
lyra_v2_action_signing/module_data/withdraw.py
lyra_v2_action_signing-0.0.7.dist-info/METADATA
lyra_v2_action_signing-0.0.7.dist-info/WHEEL
lyra_v2_action_signing-0.0.7.dist-info/top_level.txt
lyra_v2_action_signing-0.0.7.dist-info/RECORD
