Metadata-Version: 2.1
Name: lyra_v2_action_signing
Version: 0.0.7
Summary: Python package to sign on-chain self-custodial requests for orders, transfers, deposits, withdrawals and RFQs.
Author-email: Lyra Finance <joshua@lyra.finance>
Project-URL: Homepage, https://github.com/derivexyz/v2-action-signing-python
Project-URL: Issues, https://github.com/derivexyz/v2-action-signing-python/issues
Classifier: Programming Language :: Python :: 3
Classifier: License :: OSI Approved :: MIT License
Classifier: Operating System :: OS Independent
Requires-Python: >=3.9
Requires-Dist: eth-abi >=4.2.1
Requires-Dist: web3 >=6.4.0
Requires-Dist: hexbytes >=0.3.1
